{
  "name": "eat",
  "type": "GIF",
  "imageCount": 53,
  "needProcess": [0, 16],
  "pos": [
    [182, 38, 104, 86], 
    [183, 57, 96, 86], 
    [185, 61, 92, 86], 
    [185, 64, 92, 92], 
    [186, 78, 91, 92], 
    [183, 101, 94, 93], 
    [181, 121, 106, 90], 
    [159, 197, 145, 41], 
    [180, 138, 117, 65], 
    [178, 69, 116, 79], 
    [173, 45, 123, 90], 
    [177, 37, 144, 88], 
    [182, 38, 104, 86], 
    [183, 57, 96, 86], 
    [186, 61, 91, 86], 
    [185, 74, 85, 90], 
    [183, 134, 86, 95]
  ]
}